 {
    "Name": "AuRa emote voice",
    "Description": "The emote voice you are replacing",
    "Priority": 45826,
    "Type": "Single",
    "DefaultSettings": 0,
    "Options": [{
      "Name": "None",
      "Description": "",
      "Files": {},
      "FileSwaps": {},
      "Manipulations": []
    },
{"Name": "AuRa Masculine 1",
            "Description": "",
            "Priority": 45827,
            "Files": {},
            "FileSwaps": {
                "sound/voice/vo_emote/17297000.scd": "sound\\voice\\vo_emote\\7489000.scd",
"sound/voice/vo_emote/17297001.scd": "sound\\voice\\vo_emote\\7489001.scd",
"sound/voice/vo_emote/17297002.scd": "sound\\voice\\vo_emote\\7489002.scd",
"sound/voice/vo_emote/17297003.scd": "sound\\voice\\vo_emote\\7489003.scd",
"sound/voice/vo_emote/17297004.scd": "sound\\voice\\vo_emote\\7489004.scd",
"sound/voice/vo_emote/17297005.scd": "sound\\voice\\vo_emote\\7489005.scd",
"sound/voice/vo_emote/17297006.scd": "sound\\voice\\vo_emote\\7489006.scd",
"sound/voice/vo_emote/17297007.scd": "sound\\voice\\vo_emote\\7489007.scd",
"sound/voice/vo_emote/17297008.scd": "sound\\voice\\vo_emote\\7489008.scd",
"sound/voice/vo_emote/17297009.scd": "sound\\voice\\vo_emote\\7489009.scd",
"sound/voice/vo_emote/17297010.scd": "sound\\voice\\vo_emote\\7489010.scd",
"sound/voice/vo_emote/17297011.scd": "sound\\voice\\vo_emote\\7489011.scd",
"sound/voice/vo_emote/17297012.scd": "sound\\voice\\vo_emote\\7489012.scd",
"sound/voice/vo_emote/17297013.scd": "sound\\voice\\vo_emote\\7489013.scd",
"sound/voice/vo_emote/17297014.scd": "sound\\voice\\vo_emote\\7489014.scd",
"sound/voice/vo_emote/17297015.scd": "sound\\voice\\vo_emote\\7489015.scd"
            },
            "Manipulations": []
        },
{"Name": "AuRa Masculine 2",
            "Description": "",
            "Priority": 45828,
            "Files": {},
            "FileSwaps": {
                "sound/voice/vo_emote/17297000.scd": "sound\\voice\\vo_emote\\7488000.scd",
"sound/voice/vo_emote/17297001.scd": "sound\\voice\\vo_emote\\7488001.scd",
"sound/voice/vo_emote/17297002.scd": "sound\\voice\\vo_emote\\7488002.scd",
"sound/voice/vo_emote/17297003.scd": "sound\\voice\\vo_emote\\7488003.scd",
"sound/voice/vo_emote/17297004.scd": "sound\\voice\\vo_emote\\7488004.scd",
"sound/voice/vo_emote/17297005.scd": "sound\\voice\\vo_emote\\7488005.scd",
"sound/voice/vo_emote/17297006.scd": "sound\\voice\\vo_emote\\7488006.scd",
"sound/voice/vo_emote/17297007.scd": "sound\\voice\\vo_emote\\7488007.scd",
"sound/voice/vo_emote/17297008.scd": "sound\\voice\\vo_emote\\7488008.scd",
"sound/voice/vo_emote/17297009.scd": "sound\\voice\\vo_emote\\7488009.scd",
"sound/voice/vo_emote/17297010.scd": "sound\\voice\\vo_emote\\7488010.scd",
"sound/voice/vo_emote/17297011.scd": "sound\\voice\\vo_emote\\7488011.scd",
"sound/voice/vo_emote/17297012.scd": "sound\\voice\\vo_emote\\7488012.scd",
"sound/voice/vo_emote/17297013.scd": "sound\\voice\\vo_emote\\7488013.scd",
"sound/voice/vo_emote/17297014.scd": "sound\\voice\\vo_emote\\7488014.scd",
"sound/voice/vo_emote/17297015.scd": "sound\\voice\\vo_emote\\7488015.scd"
            },
            "Manipulations": []
        },
{"Name": "AuRa Masculine 3",
            "Description": "",
            "Priority": 45829,
            "Files": {},
            "FileSwaps": {
                "sound/voice/vo_emote/17297000.scd": "sound\\voice\\vo_emote\\7487000.scd",
"sound/voice/vo_emote/17297001.scd": "sound\\voice\\vo_emote\\7487001.scd",
"sound/voice/vo_emote/17297002.scd": "sound\\voice\\vo_emote\\7487002.scd",
"sound/voice/vo_emote/17297003.scd": "sound\\voice\\vo_emote\\7487003.scd",
"sound/voice/vo_emote/17297004.scd": "sound\\voice\\vo_emote\\7487004.scd",
"sound/voice/vo_emote/17297005.scd": "sound\\voice\\vo_emote\\7487005.scd",
"sound/voice/vo_emote/17297006.scd": "sound\\voice\\vo_emote\\7487006.scd",
"sound/voice/vo_emote/17297007.scd": "sound\\voice\\vo_emote\\7487007.scd",
"sound/voice/vo_emote/17297008.scd": "sound\\voice\\vo_emote\\7487008.scd",
"sound/voice/vo_emote/17297009.scd": "sound\\voice\\vo_emote\\7487009.scd",
"sound/voice/vo_emote/17297010.scd": "sound\\voice\\vo_emote\\7487010.scd",
"sound/voice/vo_emote/17297011.scd": "sound\\voice\\vo_emote\\7487011.scd",
"sound/voice/vo_emote/17297012.scd": "sound\\voice\\vo_emote\\7487012.scd",
"sound/voice/vo_emote/17297013.scd": "sound\\voice\\vo_emote\\7487013.scd",
"sound/voice/vo_emote/17297014.scd": "sound\\voice\\vo_emote\\7487014.scd",
"sound/voice/vo_emote/17297015.scd": "sound\\voice\\vo_emote\\7487015.scd"
            },
            "Manipulations": []
        },
{"Name": "AuRa Masculine 4",
            "Description": "",
            "Priority": 45830,
            "Files": {},
            "FileSwaps": {
                "sound/voice/vo_emote/17297000.scd": "sound\\voice\\vo_emote\\7439000.scd",
"sound/voice/vo_emote/17297001.scd": "sound\\voice\\vo_emote\\7439001.scd",
"sound/voice/vo_emote/17297002.scd": "sound\\voice\\vo_emote\\7439002.scd",
"sound/voice/vo_emote/17297003.scd": "sound\\voice\\vo_emote\\7439003.scd",
"sound/voice/vo_emote/17297004.scd": "sound\\voice\\vo_emote\\7439004.scd",
"sound/voice/vo_emote/17297005.scd": "sound\\voice\\vo_emote\\7439005.scd",
"sound/voice/vo_emote/17297006.scd": "sound\\voice\\vo_emote\\7439006.scd",
"sound/voice/vo_emote/17297007.scd": "sound\\voice\\vo_emote\\7439007.scd",
"sound/voice/vo_emote/17297008.scd": "sound\\voice\\vo_emote\\7439008.scd",
"sound/voice/vo_emote/17297009.scd": "sound\\voice\\vo_emote\\7439009.scd",
"sound/voice/vo_emote/17297010.scd": "sound\\voice\\vo_emote\\7439010.scd",
"sound/voice/vo_emote/17297011.scd": "sound\\voice\\vo_emote\\7439011.scd",
"sound/voice/vo_emote/17297012.scd": "sound\\voice\\vo_emote\\7439012.scd",
"sound/voice/vo_emote/17297013.scd": "sound\\voice\\vo_emote\\7439013.scd",
"sound/voice/vo_emote/17297014.scd": "sound\\voice\\vo_emote\\7439014.scd",
"sound/voice/vo_emote/17297015.scd": "sound\\voice\\vo_emote\\7439015.scd"
            },
            "Manipulations": []
        },
{"Name": "AuRa Masculine 5",
            "Description": "",
            "Priority": 45831,
            "Files": {},
            "FileSwaps": {
                "sound/voice/vo_emote/17297000.scd": "sound\\voice\\vo_emote\\7438000.scd",
"sound/voice/vo_emote/17297001.scd": "sound\\voice\\vo_emote\\7438001.scd",
"sound/voice/vo_emote/17297002.scd": "sound\\voice\\vo_emote\\7438002.scd",
"sound/voice/vo_emote/17297003.scd": "sound\\voice\\vo_emote\\7438003.scd",
"sound/voice/vo_emote/17297004.scd": "sound\\voice\\vo_emote\\7438004.scd",
"sound/voice/vo_emote/17297005.scd": "sound\\voice\\vo_emote\\7438005.scd",
"sound/voice/vo_emote/17297006.scd": "sound\\voice\\vo_emote\\7438006.scd",
"sound/voice/vo_emote/17297007.scd": "sound\\voice\\vo_emote\\7438007.scd",
"sound/voice/vo_emote/17297008.scd": "sound\\voice\\vo_emote\\7438008.scd",
"sound/voice/vo_emote/17297009.scd": "sound\\voice\\vo_emote\\7438009.scd",
"sound/voice/vo_emote/17297010.scd": "sound\\voice\\vo_emote\\7438010.scd",
"sound/voice/vo_emote/17297011.scd": "sound\\voice\\vo_emote\\7438011.scd",
"sound/voice/vo_emote/17297012.scd": "sound\\voice\\vo_emote\\7438012.scd",
"sound/voice/vo_emote/17297013.scd": "sound\\voice\\vo_emote\\7438013.scd",
"sound/voice/vo_emote/17297014.scd": "sound\\voice\\vo_emote\\7438014.scd",
"sound/voice/vo_emote/17297015.scd": "sound\\voice\\vo_emote\\7438015.scd"
            },
            "Manipulations": []
        },
{"Name": "AuRa Masculine 6",
            "Description": "",
            "Priority": 45832,
            "Files": {},
            "FileSwaps": {
                "sound/voice/vo_emote/17297000.scd": "sound\\voice\\vo_emote\\7437000.scd",
"sound/voice/vo_emote/17297001.scd": "sound\\voice\\vo_emote\\7437001.scd",
"sound/voice/vo_emote/17297002.scd": "sound\\voice\\vo_emote\\7437002.scd",
"sound/voice/vo_emote/17297003.scd": "sound\\voice\\vo_emote\\7437003.scd",
"sound/voice/vo_emote/17297004.scd": "sound\\voice\\vo_emote\\7437004.scd",
"sound/voice/vo_emote/17297005.scd": "sound\\voice\\vo_emote\\7437005.scd",
"sound/voice/vo_emote/17297006.scd": "sound\\voice\\vo_emote\\7437006.scd",
"sound/voice/vo_emote/17297007.scd": "sound\\voice\\vo_emote\\7437007.scd",
"sound/voice/vo_emote/17297008.scd": "sound\\voice\\vo_emote\\7437008.scd",
"sound/voice/vo_emote/17297009.scd": "sound\\voice\\vo_emote\\7437009.scd",
"sound/voice/vo_emote/17297010.scd": "sound\\voice\\vo_emote\\7437010.scd",
"sound/voice/vo_emote/17297011.scd": "sound\\voice\\vo_emote\\7437011.scd",
"sound/voice/vo_emote/17297012.scd": "sound\\voice\\vo_emote\\7437012.scd",
"sound/voice/vo_emote/17297013.scd": "sound\\voice\\vo_emote\\7437013.scd",
"sound/voice/vo_emote/17297014.scd": "sound\\voice\\vo_emote\\7437014.scd",
"sound/voice/vo_emote/17297015.scd": "sound\\voice\\vo_emote\\7437015.scd"
            },
            "Manipulations": []
        },
{"Name": "AuRa Masculine 7",
            "Description": "",
            "Priority": 45833,
            "Files": {},
            "FileSwaps": {
                "sound/voice/vo_emote/17297000.scd": "sound\\voice\\vo_emote\\7389000.scd",
"sound/voice/vo_emote/17297001.scd": "sound\\voice\\vo_emote\\7389001.scd",
"sound/voice/vo_emote/17297002.scd": "sound\\voice\\vo_emote\\7389002.scd",
"sound/voice/vo_emote/17297003.scd": "sound\\voice\\vo_emote\\7389003.scd",
"sound/voice/vo_emote/17297004.scd": "sound\\voice\\vo_emote\\7389004.scd",
"sound/voice/vo_emote/17297005.scd": "sound\\voice\\vo_emote\\7389005.scd",
"sound/voice/vo_emote/17297006.scd": "sound\\voice\\vo_emote\\7389006.scd",
"sound/voice/vo_emote/17297007.scd": "sound\\voice\\vo_emote\\7389007.scd",
"sound/voice/vo_emote/17297008.scd": "sound\\voice\\vo_emote\\7389008.scd",
"sound/voice/vo_emote/17297009.scd": "sound\\voice\\vo_emote\\7389009.scd",
"sound/voice/vo_emote/17297010.scd": "sound\\voice\\vo_emote\\7389010.scd",
"sound/voice/vo_emote/17297011.scd": "sound\\voice\\vo_emote\\7389011.scd",
"sound/voice/vo_emote/17297012.scd": "sound\\voice\\vo_emote\\7389012.scd",
"sound/voice/vo_emote/17297013.scd": "sound\\voice\\vo_emote\\7389013.scd",
"sound/voice/vo_emote/17297014.scd": "sound\\voice\\vo_emote\\7389014.scd",
"sound/voice/vo_emote/17297015.scd": "sound\\voice\\vo_emote\\7389015.scd"
            },
            "Manipulations": []
        },
{"Name": "AuRa Masculine 8",
            "Description": "",
            "Priority": 45834,
            "Files": {},
            "FileSwaps": {
                "sound/voice/vo_emote/17297000.scd": "sound\\voice\\vo_emote\\7388000.scd",
"sound/voice/vo_emote/17297001.scd": "sound\\voice\\vo_emote\\7388001.scd",
"sound/voice/vo_emote/17297002.scd": "sound\\voice\\vo_emote\\7388002.scd",
"sound/voice/vo_emote/17297003.scd": "sound\\voice\\vo_emote\\7388003.scd",
"sound/voice/vo_emote/17297004.scd": "sound\\voice\\vo_emote\\7388004.scd",
"sound/voice/vo_emote/17297005.scd": "sound\\voice\\vo_emote\\7388005.scd",
"sound/voice/vo_emote/17297006.scd": "sound\\voice\\vo_emote\\7388006.scd",
"sound/voice/vo_emote/17297007.scd": "sound\\voice\\vo_emote\\7388007.scd",
"sound/voice/vo_emote/17297008.scd": "sound\\voice\\vo_emote\\7388008.scd",
"sound/voice/vo_emote/17297009.scd": "sound\\voice\\vo_emote\\7388009.scd",
"sound/voice/vo_emote/17297010.scd": "sound\\voice\\vo_emote\\7388010.scd",
"sound/voice/vo_emote/17297011.scd": "sound\\voice\\vo_emote\\7388011.scd",
"sound/voice/vo_emote/17297012.scd": "sound\\voice\\vo_emote\\7388012.scd",
"sound/voice/vo_emote/17297013.scd": "sound\\voice\\vo_emote\\7388013.scd",
"sound/voice/vo_emote/17297014.scd": "sound\\voice\\vo_emote\\7388014.scd",
"sound/voice/vo_emote/17297015.scd": "sound\\voice\\vo_emote\\7388015.scd"
            },
            "Manipulations": []
        },
{"Name": "AuRa Masculine 9",
            "Description": "",
            "Priority": 45835,
            "Files": {},
            "FileSwaps": {
                "sound/voice/vo_emote/17297000.scd": "sound\\voice\\vo_emote\\7387000.scd",
"sound/voice/vo_emote/17297001.scd": "sound\\voice\\vo_emote\\7387001.scd",
"sound/voice/vo_emote/17297002.scd": "sound\\voice\\vo_emote\\7387002.scd",
"sound/voice/vo_emote/17297003.scd": "sound\\voice\\vo_emote\\7387003.scd",
"sound/voice/vo_emote/17297004.scd": "sound\\voice\\vo_emote\\7387004.scd",
"sound/voice/vo_emote/17297005.scd": "sound\\voice\\vo_emote\\7387005.scd",
"sound/voice/vo_emote/17297006.scd": "sound\\voice\\vo_emote\\7387006.scd",
"sound/voice/vo_emote/17297007.scd": "sound\\voice\\vo_emote\\7387007.scd",
"sound/voice/vo_emote/17297008.scd": "sound\\voice\\vo_emote\\7387008.scd",
"sound/voice/vo_emote/17297009.scd": "sound\\voice\\vo_emote\\7387009.scd",
"sound/voice/vo_emote/17297010.scd": "sound\\voice\\vo_emote\\7387010.scd",
"sound/voice/vo_emote/17297011.scd": "sound\\voice\\vo_emote\\7387011.scd",
"sound/voice/vo_emote/17297012.scd": "sound\\voice\\vo_emote\\7387012.scd",
"sound/voice/vo_emote/17297013.scd": "sound\\voice\\vo_emote\\7387013.scd",
"sound/voice/vo_emote/17297014.scd": "sound\\voice\\vo_emote\\7387014.scd",
"sound/voice/vo_emote/17297015.scd": "sound\\voice\\vo_emote\\7387015.scd"
            },
            "Manipulations": []
        },
{"Name": "AuRa Masculine 10",
            "Description": "",
            "Priority": 45836,
            "Files": {},
            "FileSwaps": {
                "sound/voice/vo_emote/17297000.scd": "sound\\voice\\vo_emote\\7339000.scd",
"sound/voice/vo_emote/17297001.scd": "sound\\voice\\vo_emote\\7339001.scd",
"sound/voice/vo_emote/17297002.scd": "sound\\voice\\vo_emote\\7339002.scd",
"sound/voice/vo_emote/17297003.scd": "sound\\voice\\vo_emote\\7339003.scd",
"sound/voice/vo_emote/17297004.scd": "sound\\voice\\vo_emote\\7339004.scd",
"sound/voice/vo_emote/17297005.scd": "sound\\voice\\vo_emote\\7339005.scd",
"sound/voice/vo_emote/17297006.scd": "sound\\voice\\vo_emote\\7339006.scd",
"sound/voice/vo_emote/17297007.scd": "sound\\voice\\vo_emote\\7339007.scd",
"sound/voice/vo_emote/17297008.scd": "sound\\voice\\vo_emote\\7339008.scd",
"sound/voice/vo_emote/17297009.scd": "sound\\voice\\vo_emote\\7339009.scd",
"sound/voice/vo_emote/17297010.scd": "sound\\voice\\vo_emote\\7339010.scd",
"sound/voice/vo_emote/17297011.scd": "sound\\voice\\vo_emote\\7339011.scd",
"sound/voice/vo_emote/17297012.scd": "sound\\voice\\vo_emote\\7339012.scd",
"sound/voice/vo_emote/17297013.scd": "sound\\voice\\vo_emote\\7339013.scd",
"sound/voice/vo_emote/17297014.scd": "sound\\voice\\vo_emote\\7339014.scd",
"sound/voice/vo_emote/17297015.scd": "sound\\voice\\vo_emote\\7339015.scd"
            },
            "Manipulations": []
        },
{"Name": "AuRa Masculine 11",
            "Description": "",
            "Priority": 45837,
            "Files": {},
            "FileSwaps": {
                "sound/voice/vo_emote/17297000.scd": "sound\\voice\\vo_emote\\7338000.scd",
"sound/voice/vo_emote/17297001.scd": "sound\\voice\\vo_emote\\7338001.scd",
"sound/voice/vo_emote/17297002.scd": "sound\\voice\\vo_emote\\7338002.scd",
"sound/voice/vo_emote/17297003.scd": "sound\\voice\\vo_emote\\7338003.scd",
"sound/voice/vo_emote/17297004.scd": "sound\\voice\\vo_emote\\7338004.scd",
"sound/voice/vo_emote/17297005.scd": "sound\\voice\\vo_emote\\7338005.scd",
"sound/voice/vo_emote/17297006.scd": "sound\\voice\\vo_emote\\7338006.scd",
"sound/voice/vo_emote/17297007.scd": "sound\\voice\\vo_emote\\7338007.scd",
"sound/voice/vo_emote/17297008.scd": "sound\\voice\\vo_emote\\7338008.scd",
"sound/voice/vo_emote/17297009.scd": "sound\\voice\\vo_emote\\7338009.scd",
"sound/voice/vo_emote/17297010.scd": "sound\\voice\\vo_emote\\7338010.scd",
"sound/voice/vo_emote/17297011.scd": "sound\\voice\\vo_emote\\7338011.scd",
"sound/voice/vo_emote/17297012.scd": "sound\\voice\\vo_emote\\7338012.scd",
"sound/voice/vo_emote/17297013.scd": "sound\\voice\\vo_emote\\7338013.scd",
"sound/voice/vo_emote/17297014.scd": "sound\\voice\\vo_emote\\7338014.scd",
"sound/voice/vo_emote/17297015.scd": "sound\\voice\\vo_emote\\7338015.scd"
            },
            "Manipulations": []
        },
{"Name": "AuRa Masculine 12",
            "Description": "",
            "Priority": 45838,
            "Files": {},
            "FileSwaps": {
                "sound/voice/vo_emote/17297000.scd": "sound\\voice\\vo_emote\\7337000.scd",
"sound/voice/vo_emote/17297001.scd": "sound\\voice\\vo_emote\\7337001.scd",
"sound/voice/vo_emote/17297002.scd": "sound\\voice\\vo_emote\\7337002.scd",
"sound/voice/vo_emote/17297003.scd": "sound\\voice\\vo_emote\\7337003.scd",
"sound/voice/vo_emote/17297004.scd": "sound\\voice\\vo_emote\\7337004.scd",
"sound/voice/vo_emote/17297005.scd": "sound\\voice\\vo_emote\\7337005.scd",
"sound/voice/vo_emote/17297006.scd": "sound\\voice\\vo_emote\\7337006.scd",
"sound/voice/vo_emote/17297007.scd": "sound\\voice\\vo_emote\\7337007.scd",
"sound/voice/vo_emote/17297008.scd": "sound\\voice\\vo_emote\\7337008.scd",
"sound/voice/vo_emote/17297009.scd": "sound\\voice\\vo_emote\\7337009.scd",
"sound/voice/vo_emote/17297010.scd": "sound\\voice\\vo_emote\\7337010.scd",
"sound/voice/vo_emote/17297011.scd": "sound\\voice\\vo_emote\\7337011.scd",
"sound/voice/vo_emote/17297012.scd": "sound\\voice\\vo_emote\\7337012.scd",
"sound/voice/vo_emote/17297013.scd": "sound\\voice\\vo_emote\\7337013.scd",
"sound/voice/vo_emote/17297014.scd": "sound\\voice\\vo_emote\\7337014.scd",
"sound/voice/vo_emote/17297015.scd": "sound\\voice\\vo_emote\\7337015.scd"
            },
            "Manipulations": []
        },
{"Name": "AuRa Feminine 1",
            "Description": "",
            "Priority": 45839,
            "Files": {},
            "FileSwaps": {
                "sound/voice/vo_emote/17297000.scd": "sound\\voice\\vo_emote\\7492000.scd",
"sound/voice/vo_emote/17297001.scd": "sound\\voice\\vo_emote\\7492001.scd",
"sound/voice/vo_emote/17297002.scd": "sound\\voice\\vo_emote\\7492002.scd",
"sound/voice/vo_emote/17297003.scd": "sound\\voice\\vo_emote\\7492003.scd",
"sound/voice/vo_emote/17297004.scd": "sound\\voice\\vo_emote\\7492004.scd",
"sound/voice/vo_emote/17297005.scd": "sound\\voice\\vo_emote\\7492005.scd",
"sound/voice/vo_emote/17297006.scd": "sound\\voice\\vo_emote\\7492006.scd",
"sound/voice/vo_emote/17297007.scd": "sound\\voice\\vo_emote\\7492007.scd",
"sound/voice/vo_emote/17297008.scd": "sound\\voice\\vo_emote\\7492008.scd",
"sound/voice/vo_emote/17297009.scd": "sound\\voice\\vo_emote\\7492009.scd",
"sound/voice/vo_emote/17297010.scd": "sound\\voice\\vo_emote\\7492010.scd",
"sound/voice/vo_emote/17297011.scd": "sound\\voice\\vo_emote\\7492011.scd",
"sound/voice/vo_emote/17297012.scd": "sound\\voice\\vo_emote\\7492012.scd",
"sound/voice/vo_emote/17297013.scd": "sound\\voice\\vo_emote\\7492013.scd",
"sound/voice/vo_emote/17297014.scd": "sound\\voice\\vo_emote\\7492014.scd",
"sound/voice/vo_emote/17297015.scd": "sound\\voice\\vo_emote\\7492015.scd"
            },
            "Manipulations": []
        },
{"Name": "AuRa Feminine 2",
            "Description": "",
            "Priority": 45840,
            "Files": {},
            "FileSwaps": {
                "sound/voice/vo_emote/17297000.scd": "sound\\voice\\vo_emote\\7491000.scd",
"sound/voice/vo_emote/17297001.scd": "sound\\voice\\vo_emote\\7491001.scd",
"sound/voice/vo_emote/17297002.scd": "sound\\voice\\vo_emote\\7491002.scd",
"sound/voice/vo_emote/17297003.scd": "sound\\voice\\vo_emote\\7491003.scd",
"sound/voice/vo_emote/17297004.scd": "sound\\voice\\vo_emote\\7491004.scd",
"sound/voice/vo_emote/17297005.scd": "sound\\voice\\vo_emote\\7491005.scd",
"sound/voice/vo_emote/17297006.scd": "sound\\voice\\vo_emote\\7491006.scd",
"sound/voice/vo_emote/17297007.scd": "sound\\voice\\vo_emote\\7491007.scd",
"sound/voice/vo_emote/17297008.scd": "sound\\voice\\vo_emote\\7491008.scd",
"sound/voice/vo_emote/17297009.scd": "sound\\voice\\vo_emote\\7491009.scd",
"sound/voice/vo_emote/17297010.scd": "sound\\voice\\vo_emote\\7491010.scd",
"sound/voice/vo_emote/17297011.scd": "sound\\voice\\vo_emote\\7491011.scd",
"sound/voice/vo_emote/17297012.scd": "sound\\voice\\vo_emote\\7491012.scd",
"sound/voice/vo_emote/17297013.scd": "sound\\voice\\vo_emote\\7491013.scd",
"sound/voice/vo_emote/17297014.scd": "sound\\voice\\vo_emote\\7491014.scd",
"sound/voice/vo_emote/17297015.scd": "sound\\voice\\vo_emote\\7491015.scd"
            },
            "Manipulations": []
        },
{"Name": "AuRa Feminine 3",
            "Description": "",
            "Priority": 45841,
            "Files": {},
            "FileSwaps": {
                "sound/voice/vo_emote/17297000.scd": "sound\\voice\\vo_emote\\7490000.scd",
"sound/voice/vo_emote/17297001.scd": "sound\\voice\\vo_emote\\7490001.scd",
"sound/voice/vo_emote/17297002.scd": "sound\\voice\\vo_emote\\7490002.scd",
"sound/voice/vo_emote/17297003.scd": "sound\\voice\\vo_emote\\7490003.scd",
"sound/voice/vo_emote/17297004.scd": "sound\\voice\\vo_emote\\7490004.scd",
"sound/voice/vo_emote/17297005.scd": "sound\\voice\\vo_emote\\7490005.scd",
"sound/voice/vo_emote/17297006.scd": "sound\\voice\\vo_emote\\7490006.scd",
"sound/voice/vo_emote/17297007.scd": "sound\\voice\\vo_emote\\7490007.scd",
"sound/voice/vo_emote/17297008.scd": "sound\\voice\\vo_emote\\7490008.scd",
"sound/voice/vo_emote/17297009.scd": "sound\\voice\\vo_emote\\7490009.scd",
"sound/voice/vo_emote/17297010.scd": "sound\\voice\\vo_emote\\7490010.scd",
"sound/voice/vo_emote/17297011.scd": "sound\\voice\\vo_emote\\7490011.scd",
"sound/voice/vo_emote/17297012.scd": "sound\\voice\\vo_emote\\7490012.scd",
"sound/voice/vo_emote/17297013.scd": "sound\\voice\\vo_emote\\7490013.scd",
"sound/voice/vo_emote/17297014.scd": "sound\\voice\\vo_emote\\7490014.scd",
"sound/voice/vo_emote/17297015.scd": "sound\\voice\\vo_emote\\7490015.scd"
            },
            "Manipulations": []
        },
{"Name": "AuRa Feminine 4",
            "Description": "",
            "Priority": 45842,
            "Files": {},
            "FileSwaps": {
                "sound/voice/vo_emote/17297000.scd": "sound\\voice\\vo_emote\\7442000.scd",
"sound/voice/vo_emote/17297001.scd": "sound\\voice\\vo_emote\\7442001.scd",
"sound/voice/vo_emote/17297002.scd": "sound\\voice\\vo_emote\\7442002.scd",
"sound/voice/vo_emote/17297003.scd": "sound\\voice\\vo_emote\\7442003.scd",
"sound/voice/vo_emote/17297004.scd": "sound\\voice\\vo_emote\\7442004.scd",
"sound/voice/vo_emote/17297005.scd": "sound\\voice\\vo_emote\\7442005.scd",
"sound/voice/vo_emote/17297006.scd": "sound\\voice\\vo_emote\\7442006.scd",
"sound/voice/vo_emote/17297007.scd": "sound\\voice\\vo_emote\\7442007.scd",
"sound/voice/vo_emote/17297008.scd": "sound\\voice\\vo_emote\\7442008.scd",
"sound/voice/vo_emote/17297009.scd": "sound\\voice\\vo_emote\\7442009.scd",
"sound/voice/vo_emote/17297010.scd": "sound\\voice\\vo_emote\\7442010.scd",
"sound/voice/vo_emote/17297011.scd": "sound\\voice\\vo_emote\\7442011.scd",
"sound/voice/vo_emote/17297012.scd": "sound\\voice\\vo_emote\\7442012.scd",
"sound/voice/vo_emote/17297013.scd": "sound\\voice\\vo_emote\\7442013.scd",
"sound/voice/vo_emote/17297014.scd": "sound\\voice\\vo_emote\\7442014.scd",
"sound/voice/vo_emote/17297015.scd": "sound\\voice\\vo_emote\\7442015.scd"
            },
            "Manipulations": []
        },
{"Name": "AuRa Feminine 5",
            "Description": "",
            "Priority": 45843,
            "Files": {},
            "FileSwaps": {
                "sound/voice/vo_emote/17297000.scd": "sound\\voice\\vo_emote\\7441000.scd",
"sound/voice/vo_emote/17297001.scd": "sound\\voice\\vo_emote\\7441001.scd",
"sound/voice/vo_emote/17297002.scd": "sound\\voice\\vo_emote\\7441002.scd",
"sound/voice/vo_emote/17297003.scd": "sound\\voice\\vo_emote\\7441003.scd",
"sound/voice/vo_emote/17297004.scd": "sound\\voice\\vo_emote\\7441004.scd",
"sound/voice/vo_emote/17297005.scd": "sound\\voice\\vo_emote\\7441005.scd",
"sound/voice/vo_emote/17297006.scd": "sound\\voice\\vo_emote\\7441006.scd",
"sound/voice/vo_emote/17297007.scd": "sound\\voice\\vo_emote\\7441007.scd",
"sound/voice/vo_emote/17297008.scd": "sound\\voice\\vo_emote\\7441008.scd",
"sound/voice/vo_emote/17297009.scd": "sound\\voice\\vo_emote\\7441009.scd",
"sound/voice/vo_emote/17297010.scd": "sound\\voice\\vo_emote\\7441010.scd",
"sound/voice/vo_emote/17297011.scd": "sound\\voice\\vo_emote\\7441011.scd",
"sound/voice/vo_emote/17297012.scd": "sound\\voice\\vo_emote\\7441012.scd",
"sound/voice/vo_emote/17297013.scd": "sound\\voice\\vo_emote\\7441013.scd",
"sound/voice/vo_emote/17297014.scd": "sound\\voice\\vo_emote\\7441014.scd",
"sound/voice/vo_emote/17297015.scd": "sound\\voice\\vo_emote\\7441015.scd"
            },
            "Manipulations": []
        },
{"Name": "AuRa Feminine 6",
            "Description": "",
            "Priority": 45844,
            "Files": {},
            "FileSwaps": {
                "sound/voice/vo_emote/17297000.scd": "sound\\voice\\vo_emote\\7440000.scd",
"sound/voice/vo_emote/17297001.scd": "sound\\voice\\vo_emote\\7440001.scd",
"sound/voice/vo_emote/17297002.scd": "sound\\voice\\vo_emote\\7440002.scd",
"sound/voice/vo_emote/17297003.scd": "sound\\voice\\vo_emote\\7440003.scd",
"sound/voice/vo_emote/17297004.scd": "sound\\voice\\vo_emote\\7440004.scd",
"sound/voice/vo_emote/17297005.scd": "sound\\voice\\vo_emote\\7440005.scd",
"sound/voice/vo_emote/17297006.scd": "sound\\voice\\vo_emote\\7440006.scd",
"sound/voice/vo_emote/17297007.scd": "sound\\voice\\vo_emote\\7440007.scd",
"sound/voice/vo_emote/17297008.scd": "sound\\voice\\vo_emote\\7440008.scd",
"sound/voice/vo_emote/17297009.scd": "sound\\voice\\vo_emote\\7440009.scd",
"sound/voice/vo_emote/17297010.scd": "sound\\voice\\vo_emote\\7440010.scd",
"sound/voice/vo_emote/17297011.scd": "sound\\voice\\vo_emote\\7440011.scd",
"sound/voice/vo_emote/17297012.scd": "sound\\voice\\vo_emote\\7440012.scd",
"sound/voice/vo_emote/17297013.scd": "sound\\voice\\vo_emote\\7440013.scd",
"sound/voice/vo_emote/17297014.scd": "sound\\voice\\vo_emote\\7440014.scd",
"sound/voice/vo_emote/17297015.scd": "sound\\voice\\vo_emote\\7440015.scd"
            },
            "Manipulations": []
        },
{"Name": "AuRa Feminine 7",
            "Description": "",
            "Priority": 45845,
            "Files": {},
            "FileSwaps": {
                "sound/voice/vo_emote/17297000.scd": "sound\\voice\\vo_emote\\7392000.scd",
"sound/voice/vo_emote/17297001.scd": "sound\\voice\\vo_emote\\7392001.scd",
"sound/voice/vo_emote/17297002.scd": "sound\\voice\\vo_emote\\7392002.scd",
"sound/voice/vo_emote/17297003.scd": "sound\\voice\\vo_emote\\7392003.scd",
"sound/voice/vo_emote/17297004.scd": "sound\\voice\\vo_emote\\7392004.scd",
"sound/voice/vo_emote/17297005.scd": "sound\\voice\\vo_emote\\7392005.scd",
"sound/voice/vo_emote/17297006.scd": "sound\\voice\\vo_emote\\7392006.scd",
"sound/voice/vo_emote/17297007.scd": "sound\\voice\\vo_emote\\7392007.scd",
"sound/voice/vo_emote/17297008.scd": "sound\\voice\\vo_emote\\7392008.scd",
"sound/voice/vo_emote/17297009.scd": "sound\\voice\\vo_emote\\7392009.scd",
"sound/voice/vo_emote/17297010.scd": "sound\\voice\\vo_emote\\7392010.scd",
"sound/voice/vo_emote/17297011.scd": "sound\\voice\\vo_emote\\7392011.scd",
"sound/voice/vo_emote/17297012.scd": "sound\\voice\\vo_emote\\7392012.scd",
"sound/voice/vo_emote/17297013.scd": "sound\\voice\\vo_emote\\7392013.scd",
"sound/voice/vo_emote/17297014.scd": "sound\\voice\\vo_emote\\7392014.scd",
"sound/voice/vo_emote/17297015.scd": "sound\\voice\\vo_emote\\7392015.scd"
            },
            "Manipulations": []
        },
{"Name": "AuRa Feminine 8",
            "Description": "",
            "Priority": 45846,
            "Files": {},
            "FileSwaps": {
                "sound/voice/vo_emote/17297000.scd": "sound\\voice\\vo_emote\\7391000.scd",
"sound/voice/vo_emote/17297001.scd": "sound\\voice\\vo_emote\\7391001.scd",
"sound/voice/vo_emote/17297002.scd": "sound\\voice\\vo_emote\\7391002.scd",
"sound/voice/vo_emote/17297003.scd": "sound\\voice\\vo_emote\\7391003.scd",
"sound/voice/vo_emote/17297004.scd": "sound\\voice\\vo_emote\\7391004.scd",
"sound/voice/vo_emote/17297005.scd": "sound\\voice\\vo_emote\\7391005.scd",
"sound/voice/vo_emote/17297006.scd": "sound\\voice\\vo_emote\\7391006.scd",
"sound/voice/vo_emote/17297007.scd": "sound\\voice\\vo_emote\\7391007.scd",
"sound/voice/vo_emote/17297008.scd": "sound\\voice\\vo_emote\\7391008.scd",
"sound/voice/vo_emote/17297009.scd": "sound\\voice\\vo_emote\\7391009.scd",
"sound/voice/vo_emote/17297010.scd": "sound\\voice\\vo_emote\\7391010.scd",
"sound/voice/vo_emote/17297011.scd": "sound\\voice\\vo_emote\\7391011.scd",
"sound/voice/vo_emote/17297012.scd": "sound\\voice\\vo_emote\\7391012.scd",
"sound/voice/vo_emote/17297013.scd": "sound\\voice\\vo_emote\\7391013.scd",
"sound/voice/vo_emote/17297014.scd": "sound\\voice\\vo_emote\\7391014.scd",
"sound/voice/vo_emote/17297015.scd": "sound\\voice\\vo_emote\\7391015.scd"
            },
            "Manipulations": []
        },
{"Name": "AuRa Feminine 9",
            "Description": "",
            "Priority": 45847,
            "Files": {},
            "FileSwaps": {
                "sound/voice/vo_emote/17297000.scd": "sound\\voice\\vo_emote\\7390000.scd",
"sound/voice/vo_emote/17297001.scd": "sound\\voice\\vo_emote\\7390001.scd",
"sound/voice/vo_emote/17297002.scd": "sound\\voice\\vo_emote\\7390002.scd",
"sound/voice/vo_emote/17297003.scd": "sound\\voice\\vo_emote\\7390003.scd",
"sound/voice/vo_emote/17297004.scd": "sound\\voice\\vo_emote\\7390004.scd",
"sound/voice/vo_emote/17297005.scd": "sound\\voice\\vo_emote\\7390005.scd",
"sound/voice/vo_emote/17297006.scd": "sound\\voice\\vo_emote\\7390006.scd",
"sound/voice/vo_emote/17297007.scd": "sound\\voice\\vo_emote\\7390007.scd",
"sound/voice/vo_emote/17297008.scd": "sound\\voice\\vo_emote\\7390008.scd",
"sound/voice/vo_emote/17297009.scd": "sound\\voice\\vo_emote\\7390009.scd",
"sound/voice/vo_emote/17297010.scd": "sound\\voice\\vo_emote\\7390010.scd",
"sound/voice/vo_emote/17297011.scd": "sound\\voice\\vo_emote\\7390011.scd",
"sound/voice/vo_emote/17297012.scd": "sound\\voice\\vo_emote\\7390012.scd",
"sound/voice/vo_emote/17297013.scd": "sound\\voice\\vo_emote\\7390013.scd",
"sound/voice/vo_emote/17297014.scd": "sound\\voice\\vo_emote\\7390014.scd",
"sound/voice/vo_emote/17297015.scd": "sound\\voice\\vo_emote\\7390015.scd"
            },
            "Manipulations": []
        },
{"Name": "AuRa Feminine 10",
            "Description": "",
            "Priority": 45848,
            "Files": {},
            "FileSwaps": {
                "sound/voice/vo_emote/17297000.scd": "sound\\voice\\vo_emote\\7342000.scd",
"sound/voice/vo_emote/17297001.scd": "sound\\voice\\vo_emote\\7342001.scd",
"sound/voice/vo_emote/17297002.scd": "sound\\voice\\vo_emote\\7342002.scd",
"sound/voice/vo_emote/17297003.scd": "sound\\voice\\vo_emote\\7342003.scd",
"sound/voice/vo_emote/17297004.scd": "sound\\voice\\vo_emote\\7342004.scd",
"sound/voice/vo_emote/17297005.scd": "sound\\voice\\vo_emote\\7342005.scd",
"sound/voice/vo_emote/17297006.scd": "sound\\voice\\vo_emote\\7342006.scd",
"sound/voice/vo_emote/17297007.scd": "sound\\voice\\vo_emote\\7342007.scd",
"sound/voice/vo_emote/17297008.scd": "sound\\voice\\vo_emote\\7342008.scd",
"sound/voice/vo_emote/17297009.scd": "sound\\voice\\vo_emote\\7342009.scd",
"sound/voice/vo_emote/17297010.scd": "sound\\voice\\vo_emote\\7342010.scd",
"sound/voice/vo_emote/17297011.scd": "sound\\voice\\vo_emote\\7342011.scd",
"sound/voice/vo_emote/17297012.scd": "sound\\voice\\vo_emote\\7342012.scd",
"sound/voice/vo_emote/17297013.scd": "sound\\voice\\vo_emote\\7342013.scd",
"sound/voice/vo_emote/17297014.scd": "sound\\voice\\vo_emote\\7342014.scd",
"sound/voice/vo_emote/17297015.scd": "sound\\voice\\vo_emote\\7342015.scd"
            },
            "Manipulations": []
        },
{"Name": "AuRa Feminine 11",
            "Description": "",
            "Priority": 45849,
            "Files": {},
            "FileSwaps": {
                "sound/voice/vo_emote/17297000.scd": "sound\\voice\\vo_emote\\7341000.scd",
"sound/voice/vo_emote/17297001.scd": "sound\\voice\\vo_emote\\7341001.scd",
"sound/voice/vo_emote/17297002.scd": "sound\\voice\\vo_emote\\7341002.scd",
"sound/voice/vo_emote/17297003.scd": "sound\\voice\\vo_emote\\7341003.scd",
"sound/voice/vo_emote/17297004.scd": "sound\\voice\\vo_emote\\7341004.scd",
"sound/voice/vo_emote/17297005.scd": "sound\\voice\\vo_emote\\7341005.scd",
"sound/voice/vo_emote/17297006.scd": "sound\\voice\\vo_emote\\7341006.scd",
"sound/voice/vo_emote/17297007.scd": "sound\\voice\\vo_emote\\7341007.scd",
"sound/voice/vo_emote/17297008.scd": "sound\\voice\\vo_emote\\7341008.scd",
"sound/voice/vo_emote/17297009.scd": "sound\\voice\\vo_emote\\7341009.scd",
"sound/voice/vo_emote/17297010.scd": "sound\\voice\\vo_emote\\7341010.scd",
"sound/voice/vo_emote/17297011.scd": "sound\\voice\\vo_emote\\7341011.scd",
"sound/voice/vo_emote/17297012.scd": "sound\\voice\\vo_emote\\7341012.scd",
"sound/voice/vo_emote/17297013.scd": "sound\\voice\\vo_emote\\7341013.scd",
"sound/voice/vo_emote/17297014.scd": "sound\\voice\\vo_emote\\7341014.scd",
"sound/voice/vo_emote/17297015.scd": "sound\\voice\\vo_emote\\7341015.scd"
            },
            "Manipulations": []
        },
{"Name": "AuRa Feminine 12",
            "Description": "",
            "Priority": 45850,
            "Files": {},
            "FileSwaps": {
                "sound/voice/vo_emote/17297000.scd": "sound\\voice\\vo_emote\\7340000.scd",
"sound/voice/vo_emote/17297001.scd": "sound\\voice\\vo_emote\\7340001.scd",
"sound/voice/vo_emote/17297002.scd": "sound\\voice\\vo_emote\\7340002.scd",
"sound/voice/vo_emote/17297003.scd": "sound\\voice\\vo_emote\\7340003.scd",
"sound/voice/vo_emote/17297004.scd": "sound\\voice\\vo_emote\\7340004.scd",
"sound/voice/vo_emote/17297005.scd": "sound\\voice\\vo_emote\\7340005.scd",
"sound/voice/vo_emote/17297006.scd": "sound\\voice\\vo_emote\\7340006.scd",
"sound/voice/vo_emote/17297007.scd": "sound\\voice\\vo_emote\\7340007.scd",
"sound/voice/vo_emote/17297008.scd": "sound\\voice\\vo_emote\\7340008.scd",
"sound/voice/vo_emote/17297009.scd": "sound\\voice\\vo_emote\\7340009.scd",
"sound/voice/vo_emote/17297010.scd": "sound\\voice\\vo_emote\\7340010.scd",
"sound/voice/vo_emote/17297011.scd": "sound\\voice\\vo_emote\\7340011.scd",
"sound/voice/vo_emote/17297012.scd": "sound\\voice\\vo_emote\\7340012.scd",
"sound/voice/vo_emote/17297013.scd": "sound\\voice\\vo_emote\\7340013.scd",
"sound/voice/vo_emote/17297014.scd": "sound\\voice\\vo_emote\\7340014.scd",
"sound/voice/vo_emote/17297015.scd": "sound\\voice\\vo_emote\\7340015.scd"
            },
            "Manipulations": []
        }]
    }