 {
    "Name": "Viera emote voice",
    "Description": "The emote voice you are replacing",
    "Priority": 40701,
    "Type": "Single",
    "DefaultSettings": 0,
    "Options": [{
      "Name": "None",
      "Description": "",
      "Files": {},
      "FileSwaps": {},
      "Manipulations": []
    },
{"Name": "Viera Masculine 1",
            "Description": "",
            "Priority": 40702,
            "Files": {},
            "FileSwaps": {
                "sound/voice/vo_emote/17462000.scd": "sound\\voice\\vo_emote\\17459000.scd",
"sound/voice/vo_emote/17462001.scd": "sound\\voice\\vo_emote\\17459001.scd",
"sound/voice/vo_emote/17462002.scd": "sound\\voice\\vo_emote\\17459002.scd",
"sound/voice/vo_emote/17462003.scd": "sound\\voice\\vo_emote\\17459003.scd",
"sound/voice/vo_emote/17462004.scd": "sound\\voice\\vo_emote\\17459004.scd",
"sound/voice/vo_emote/17462005.scd": "sound\\voice\\vo_emote\\17459005.scd",
"sound/voice/vo_emote/17462006.scd": "sound\\voice\\vo_emote\\17459006.scd",
"sound/voice/vo_emote/17462007.scd": "sound\\voice\\vo_emote\\17459007.scd",
"sound/voice/vo_emote/17462008.scd": "sound\\voice\\vo_emote\\17459008.scd",
"sound/voice/vo_emote/17462009.scd": "sound\\voice\\vo_emote\\17459009.scd",
"sound/voice/vo_emote/17462010.scd": "sound\\voice\\vo_emote\\17459010.scd",
"sound/voice/vo_emote/17462011.scd": "sound\\voice\\vo_emote\\17459011.scd",
"sound/voice/vo_emote/17462012.scd": "sound\\voice\\vo_emote\\17459012.scd",
"sound/voice/vo_emote/17462013.scd": "sound\\voice\\vo_emote\\17459013.scd",
"sound/voice/vo_emote/17462014.scd": "sound\\voice\\vo_emote\\17459014.scd",
"sound/voice/vo_emote/17462015.scd": "sound\\voice\\vo_emote\\17459015.scd"
            },
            "Manipulations": []
        },
{"Name": "Viera Masculine 2",
            "Description": "",
            "Priority": 40703,
            "Files": {},
            "FileSwaps": {
                "sound/voice/vo_emote/17462000.scd": "sound\\voice\\vo_emote\\17458000.scd",
"sound/voice/vo_emote/17462001.scd": "sound\\voice\\vo_emote\\17458001.scd",
"sound/voice/vo_emote/17462002.scd": "sound\\voice\\vo_emote\\17458002.scd",
"sound/voice/vo_emote/17462003.scd": "sound\\voice\\vo_emote\\17458003.scd",
"sound/voice/vo_emote/17462004.scd": "sound\\voice\\vo_emote\\17458004.scd",
"sound/voice/vo_emote/17462005.scd": "sound\\voice\\vo_emote\\17458005.scd",
"sound/voice/vo_emote/17462006.scd": "sound\\voice\\vo_emote\\17458006.scd",
"sound/voice/vo_emote/17462007.scd": "sound\\voice\\vo_emote\\17458007.scd",
"sound/voice/vo_emote/17462008.scd": "sound\\voice\\vo_emote\\17458008.scd",
"sound/voice/vo_emote/17462009.scd": "sound\\voice\\vo_emote\\17458009.scd",
"sound/voice/vo_emote/17462010.scd": "sound\\voice\\vo_emote\\17458010.scd",
"sound/voice/vo_emote/17462011.scd": "sound\\voice\\vo_emote\\17458011.scd",
"sound/voice/vo_emote/17462012.scd": "sound\\voice\\vo_emote\\17458012.scd",
"sound/voice/vo_emote/17462013.scd": "sound\\voice\\vo_emote\\17458013.scd",
"sound/voice/vo_emote/17462014.scd": "sound\\voice\\vo_emote\\17458014.scd",
"sound/voice/vo_emote/17462015.scd": "sound\\voice\\vo_emote\\17458015.scd"
            },
            "Manipulations": []
        },
{"Name": "Viera Masculine 3",
            "Description": "",
            "Priority": 40704,
            "Files": {},
            "FileSwaps": {
                "sound/voice/vo_emote/17462000.scd": "sound\\voice\\vo_emote\\17457000.scd",
"sound/voice/vo_emote/17462001.scd": "sound\\voice\\vo_emote\\17457001.scd",
"sound/voice/vo_emote/17462002.scd": "sound\\voice\\vo_emote\\17457002.scd",
"sound/voice/vo_emote/17462003.scd": "sound\\voice\\vo_emote\\17457003.scd",
"sound/voice/vo_emote/17462004.scd": "sound\\voice\\vo_emote\\17457004.scd",
"sound/voice/vo_emote/17462005.scd": "sound\\voice\\vo_emote\\17457005.scd",
"sound/voice/vo_emote/17462006.scd": "sound\\voice\\vo_emote\\17457006.scd",
"sound/voice/vo_emote/17462007.scd": "sound\\voice\\vo_emote\\17457007.scd",
"sound/voice/vo_emote/17462008.scd": "sound\\voice\\vo_emote\\17457008.scd",
"sound/voice/vo_emote/17462009.scd": "sound\\voice\\vo_emote\\17457009.scd",
"sound/voice/vo_emote/17462010.scd": "sound\\voice\\vo_emote\\17457010.scd",
"sound/voice/vo_emote/17462011.scd": "sound\\voice\\vo_emote\\17457011.scd",
"sound/voice/vo_emote/17462012.scd": "sound\\voice\\vo_emote\\17457012.scd",
"sound/voice/vo_emote/17462013.scd": "sound\\voice\\vo_emote\\17457013.scd",
"sound/voice/vo_emote/17462014.scd": "sound\\voice\\vo_emote\\17457014.scd",
"sound/voice/vo_emote/17462015.scd": "sound\\voice\\vo_emote\\17457015.scd"
            },
            "Manipulations": []
        },
{"Name": "Viera Masculine 4",
            "Description": "",
            "Priority": 40705,
            "Files": {},
            "FileSwaps": {
                "sound/voice/vo_emote/17462000.scd": "sound\\voice\\vo_emote\\17409000.scd",
"sound/voice/vo_emote/17462001.scd": "sound\\voice\\vo_emote\\17409001.scd",
"sound/voice/vo_emote/17462002.scd": "sound\\voice\\vo_emote\\17409002.scd",
"sound/voice/vo_emote/17462003.scd": "sound\\voice\\vo_emote\\17409003.scd",
"sound/voice/vo_emote/17462004.scd": "sound\\voice\\vo_emote\\17409004.scd",
"sound/voice/vo_emote/17462005.scd": "sound\\voice\\vo_emote\\17409005.scd",
"sound/voice/vo_emote/17462006.scd": "sound\\voice\\vo_emote\\17409006.scd",
"sound/voice/vo_emote/17462007.scd": "sound\\voice\\vo_emote\\17409007.scd",
"sound/voice/vo_emote/17462008.scd": "sound\\voice\\vo_emote\\17409008.scd",
"sound/voice/vo_emote/17462009.scd": "sound\\voice\\vo_emote\\17409009.scd",
"sound/voice/vo_emote/17462010.scd": "sound\\voice\\vo_emote\\17409010.scd",
"sound/voice/vo_emote/17462011.scd": "sound\\voice\\vo_emote\\17409011.scd",
"sound/voice/vo_emote/17462012.scd": "sound\\voice\\vo_emote\\17409012.scd",
"sound/voice/vo_emote/17462013.scd": "sound\\voice\\vo_emote\\17409013.scd",
"sound/voice/vo_emote/17462014.scd": "sound\\voice\\vo_emote\\17409014.scd",
"sound/voice/vo_emote/17462015.scd": "sound\\voice\\vo_emote\\17409015.scd"
            },
            "Manipulations": []
        },
{"Name": "Viera Masculine 5",
            "Description": "",
            "Priority": 40706,
            "Files": {},
            "FileSwaps": {
                "sound/voice/vo_emote/17462000.scd": "sound\\voice\\vo_emote\\17408000.scd",
"sound/voice/vo_emote/17462001.scd": "sound\\voice\\vo_emote\\17408001.scd",
"sound/voice/vo_emote/17462002.scd": "sound\\voice\\vo_emote\\17408002.scd",
"sound/voice/vo_emote/17462003.scd": "sound\\voice\\vo_emote\\17408003.scd",
"sound/voice/vo_emote/17462004.scd": "sound\\voice\\vo_emote\\17408004.scd",
"sound/voice/vo_emote/17462005.scd": "sound\\voice\\vo_emote\\17408005.scd",
"sound/voice/vo_emote/17462006.scd": "sound\\voice\\vo_emote\\17408006.scd",
"sound/voice/vo_emote/17462007.scd": "sound\\voice\\vo_emote\\17408007.scd",
"sound/voice/vo_emote/17462008.scd": "sound\\voice\\vo_emote\\17408008.scd",
"sound/voice/vo_emote/17462009.scd": "sound\\voice\\vo_emote\\17408009.scd",
"sound/voice/vo_emote/17462010.scd": "sound\\voice\\vo_emote\\17408010.scd",
"sound/voice/vo_emote/17462011.scd": "sound\\voice\\vo_emote\\17408011.scd",
"sound/voice/vo_emote/17462012.scd": "sound\\voice\\vo_emote\\17408012.scd",
"sound/voice/vo_emote/17462013.scd": "sound\\voice\\vo_emote\\17408013.scd",
"sound/voice/vo_emote/17462014.scd": "sound\\voice\\vo_emote\\17408014.scd",
"sound/voice/vo_emote/17462015.scd": "sound\\voice\\vo_emote\\17408015.scd"
            },
            "Manipulations": []
        },
{"Name": "Viera Masculine 6",
            "Description": "",
            "Priority": 40707,
            "Files": {},
            "FileSwaps": {
                "sound/voice/vo_emote/17462000.scd": "sound\\voice\\vo_emote\\17407000.scd",
"sound/voice/vo_emote/17462001.scd": "sound\\voice\\vo_emote\\17407001.scd",
"sound/voice/vo_emote/17462002.scd": "sound\\voice\\vo_emote\\17407002.scd",
"sound/voice/vo_emote/17462003.scd": "sound\\voice\\vo_emote\\17407003.scd",
"sound/voice/vo_emote/17462004.scd": "sound\\voice\\vo_emote\\17407004.scd",
"sound/voice/vo_emote/17462005.scd": "sound\\voice\\vo_emote\\17407005.scd",
"sound/voice/vo_emote/17462006.scd": "sound\\voice\\vo_emote\\17407006.scd",
"sound/voice/vo_emote/17462007.scd": "sound\\voice\\vo_emote\\17407007.scd",
"sound/voice/vo_emote/17462008.scd": "sound\\voice\\vo_emote\\17407008.scd",
"sound/voice/vo_emote/17462009.scd": "sound\\voice\\vo_emote\\17407009.scd",
"sound/voice/vo_emote/17462010.scd": "sound\\voice\\vo_emote\\17407010.scd",
"sound/voice/vo_emote/17462011.scd": "sound\\voice\\vo_emote\\17407011.scd",
"sound/voice/vo_emote/17462012.scd": "sound\\voice\\vo_emote\\17407012.scd",
"sound/voice/vo_emote/17462013.scd": "sound\\voice\\vo_emote\\17407013.scd",
"sound/voice/vo_emote/17462014.scd": "sound\\voice\\vo_emote\\17407014.scd",
"sound/voice/vo_emote/17462015.scd": "sound\\voice\\vo_emote\\17407015.scd"
            },
            "Manipulations": []
        },
{"Name": "Viera Masculine 7",
            "Description": "",
            "Priority": 40708,
            "Files": {},
            "FileSwaps": {
                "sound/voice/vo_emote/17462000.scd": "sound\\voice\\vo_emote\\17359000.scd",
"sound/voice/vo_emote/17462001.scd": "sound\\voice\\vo_emote\\17359001.scd",
"sound/voice/vo_emote/17462002.scd": "sound\\voice\\vo_emote\\17359002.scd",
"sound/voice/vo_emote/17462003.scd": "sound\\voice\\vo_emote\\17359003.scd",
"sound/voice/vo_emote/17462004.scd": "sound\\voice\\vo_emote\\17359004.scd",
"sound/voice/vo_emote/17462005.scd": "sound\\voice\\vo_emote\\17359005.scd",
"sound/voice/vo_emote/17462006.scd": "sound\\voice\\vo_emote\\17359006.scd",
"sound/voice/vo_emote/17462007.scd": "sound\\voice\\vo_emote\\17359007.scd",
"sound/voice/vo_emote/17462008.scd": "sound\\voice\\vo_emote\\17359008.scd",
"sound/voice/vo_emote/17462009.scd": "sound\\voice\\vo_emote\\17359009.scd",
"sound/voice/vo_emote/17462010.scd": "sound\\voice\\vo_emote\\17359010.scd",
"sound/voice/vo_emote/17462011.scd": "sound\\voice\\vo_emote\\17359011.scd",
"sound/voice/vo_emote/17462012.scd": "sound\\voice\\vo_emote\\17359012.scd",
"sound/voice/vo_emote/17462013.scd": "sound\\voice\\vo_emote\\17359013.scd",
"sound/voice/vo_emote/17462014.scd": "sound\\voice\\vo_emote\\17359014.scd",
"sound/voice/vo_emote/17462015.scd": "sound\\voice\\vo_emote\\17359015.scd"
            },
            "Manipulations": []
        },
{"Name": "Viera Masculine 8",
            "Description": "",
            "Priority": 40709,
            "Files": {},
            "FileSwaps": {
                "sound/voice/vo_emote/17462000.scd": "sound\\voice\\vo_emote\\17358000.scd",
"sound/voice/vo_emote/17462001.scd": "sound\\voice\\vo_emote\\17358001.scd",
"sound/voice/vo_emote/17462002.scd": "sound\\voice\\vo_emote\\17358002.scd",
"sound/voice/vo_emote/17462003.scd": "sound\\voice\\vo_emote\\17358003.scd",
"sound/voice/vo_emote/17462004.scd": "sound\\voice\\vo_emote\\17358004.scd",
"sound/voice/vo_emote/17462005.scd": "sound\\voice\\vo_emote\\17358005.scd",
"sound/voice/vo_emote/17462006.scd": "sound\\voice\\vo_emote\\17358006.scd",
"sound/voice/vo_emote/17462007.scd": "sound\\voice\\vo_emote\\17358007.scd",
"sound/voice/vo_emote/17462008.scd": "sound\\voice\\vo_emote\\17358008.scd",
"sound/voice/vo_emote/17462009.scd": "sound\\voice\\vo_emote\\17358009.scd",
"sound/voice/vo_emote/17462010.scd": "sound\\voice\\vo_emote\\17358010.scd",
"sound/voice/vo_emote/17462011.scd": "sound\\voice\\vo_emote\\17358011.scd",
"sound/voice/vo_emote/17462012.scd": "sound\\voice\\vo_emote\\17358012.scd",
"sound/voice/vo_emote/17462013.scd": "sound\\voice\\vo_emote\\17358013.scd",
"sound/voice/vo_emote/17462014.scd": "sound\\voice\\vo_emote\\17358014.scd",
"sound/voice/vo_emote/17462015.scd": "sound\\voice\\vo_emote\\17358015.scd"
            },
            "Manipulations": []
        },
{"Name": "Viera Masculine 9",
            "Description": "",
            "Priority": 40710,
            "Files": {},
            "FileSwaps": {
                "sound/voice/vo_emote/17462000.scd": "sound\\voice\\vo_emote\\17357000.scd",
"sound/voice/vo_emote/17462001.scd": "sound\\voice\\vo_emote\\17357001.scd",
"sound/voice/vo_emote/17462002.scd": "sound\\voice\\vo_emote\\17357002.scd",
"sound/voice/vo_emote/17462003.scd": "sound\\voice\\vo_emote\\17357003.scd",
"sound/voice/vo_emote/17462004.scd": "sound\\voice\\vo_emote\\17357004.scd",
"sound/voice/vo_emote/17462005.scd": "sound\\voice\\vo_emote\\17357005.scd",
"sound/voice/vo_emote/17462006.scd": "sound\\voice\\vo_emote\\17357006.scd",
"sound/voice/vo_emote/17462007.scd": "sound\\voice\\vo_emote\\17357007.scd",
"sound/voice/vo_emote/17462008.scd": "sound\\voice\\vo_emote\\17357008.scd",
"sound/voice/vo_emote/17462009.scd": "sound\\voice\\vo_emote\\17357009.scd",
"sound/voice/vo_emote/17462010.scd": "sound\\voice\\vo_emote\\17357010.scd",
"sound/voice/vo_emote/17462011.scd": "sound\\voice\\vo_emote\\17357011.scd",
"sound/voice/vo_emote/17462012.scd": "sound\\voice\\vo_emote\\17357012.scd",
"sound/voice/vo_emote/17462013.scd": "sound\\voice\\vo_emote\\17357013.scd",
"sound/voice/vo_emote/17462014.scd": "sound\\voice\\vo_emote\\17357014.scd",
"sound/voice/vo_emote/17462015.scd": "sound\\voice\\vo_emote\\17357015.scd"
            },
            "Manipulations": []
        },
{"Name": "Viera Masculine 10",
            "Description": "",
            "Priority": 40711,
            "Files": {},
            "FileSwaps": {
                "sound/voice/vo_emote/17462000.scd": "sound\\voice\\vo_emote\\17309000.scd",
"sound/voice/vo_emote/17462001.scd": "sound\\voice\\vo_emote\\17309001.scd",
"sound/voice/vo_emote/17462002.scd": "sound\\voice\\vo_emote\\17309002.scd",
"sound/voice/vo_emote/17462003.scd": "sound\\voice\\vo_emote\\17309003.scd",
"sound/voice/vo_emote/17462004.scd": "sound\\voice\\vo_emote\\17309004.scd",
"sound/voice/vo_emote/17462005.scd": "sound\\voice\\vo_emote\\17309005.scd",
"sound/voice/vo_emote/17462006.scd": "sound\\voice\\vo_emote\\17309006.scd",
"sound/voice/vo_emote/17462007.scd": "sound\\voice\\vo_emote\\17309007.scd",
"sound/voice/vo_emote/17462008.scd": "sound\\voice\\vo_emote\\17309008.scd",
"sound/voice/vo_emote/17462009.scd": "sound\\voice\\vo_emote\\17309009.scd",
"sound/voice/vo_emote/17462010.scd": "sound\\voice\\vo_emote\\17309010.scd",
"sound/voice/vo_emote/17462011.scd": "sound\\voice\\vo_emote\\17309011.scd",
"sound/voice/vo_emote/17462012.scd": "sound\\voice\\vo_emote\\17309012.scd",
"sound/voice/vo_emote/17462013.scd": "sound\\voice\\vo_emote\\17309013.scd",
"sound/voice/vo_emote/17462014.scd": "sound\\voice\\vo_emote\\17309014.scd",
"sound/voice/vo_emote/17462015.scd": "sound\\voice\\vo_emote\\17309015.scd"
            },
            "Manipulations": []
        },
{"Name": "Viera Masculine 11",
            "Description": "",
            "Priority": 40712,
            "Files": {},
            "FileSwaps": {
                "sound/voice/vo_emote/17462000.scd": "sound\\voice\\vo_emote\\17308000.scd",
"sound/voice/vo_emote/17462001.scd": "sound\\voice\\vo_emote\\17308001.scd",
"sound/voice/vo_emote/17462002.scd": "sound\\voice\\vo_emote\\17308002.scd",
"sound/voice/vo_emote/17462003.scd": "sound\\voice\\vo_emote\\17308003.scd",
"sound/voice/vo_emote/17462004.scd": "sound\\voice\\vo_emote\\17308004.scd",
"sound/voice/vo_emote/17462005.scd": "sound\\voice\\vo_emote\\17308005.scd",
"sound/voice/vo_emote/17462006.scd": "sound\\voice\\vo_emote\\17308006.scd",
"sound/voice/vo_emote/17462007.scd": "sound\\voice\\vo_emote\\17308007.scd",
"sound/voice/vo_emote/17462008.scd": "sound\\voice\\vo_emote\\17308008.scd",
"sound/voice/vo_emote/17462009.scd": "sound\\voice\\vo_emote\\17308009.scd",
"sound/voice/vo_emote/17462010.scd": "sound\\voice\\vo_emote\\17308010.scd",
"sound/voice/vo_emote/17462011.scd": "sound\\voice\\vo_emote\\17308011.scd",
"sound/voice/vo_emote/17462012.scd": "sound\\voice\\vo_emote\\17308012.scd",
"sound/voice/vo_emote/17462013.scd": "sound\\voice\\vo_emote\\17308013.scd",
"sound/voice/vo_emote/17462014.scd": "sound\\voice\\vo_emote\\17308014.scd",
"sound/voice/vo_emote/17462015.scd": "sound\\voice\\vo_emote\\17308015.scd"
            },
            "Manipulations": []
        },
{"Name": "Viera Masculine 12",
            "Description": "",
            "Priority": 40713,
            "Files": {},
            "FileSwaps": {
                "sound/voice/vo_emote/17462000.scd": "sound\\voice\\vo_emote\\17307000.scd",
"sound/voice/vo_emote/17462001.scd": "sound\\voice\\vo_emote\\17307001.scd",
"sound/voice/vo_emote/17462002.scd": "sound\\voice\\vo_emote\\17307002.scd",
"sound/voice/vo_emote/17462003.scd": "sound\\voice\\vo_emote\\17307003.scd",
"sound/voice/vo_emote/17462004.scd": "sound\\voice\\vo_emote\\17307004.scd",
"sound/voice/vo_emote/17462005.scd": "sound\\voice\\vo_emote\\17307005.scd",
"sound/voice/vo_emote/17462006.scd": "sound\\voice\\vo_emote\\17307006.scd",
"sound/voice/vo_emote/17462007.scd": "sound\\voice\\vo_emote\\17307007.scd",
"sound/voice/vo_emote/17462008.scd": "sound\\voice\\vo_emote\\17307008.scd",
"sound/voice/vo_emote/17462009.scd": "sound\\voice\\vo_emote\\17307009.scd",
"sound/voice/vo_emote/17462010.scd": "sound\\voice\\vo_emote\\17307010.scd",
"sound/voice/vo_emote/17462011.scd": "sound\\voice\\vo_emote\\17307011.scd",
"sound/voice/vo_emote/17462012.scd": "sound\\voice\\vo_emote\\17307012.scd",
"sound/voice/vo_emote/17462013.scd": "sound\\voice\\vo_emote\\17307013.scd",
"sound/voice/vo_emote/17462014.scd": "sound\\voice\\vo_emote\\17307014.scd",
"sound/voice/vo_emote/17462015.scd": "sound\\voice\\vo_emote\\17307015.scd"
            },
            "Manipulations": []
        },
{"Name": "Viera Feminine 1",
            "Description": "",
            "Priority": 40714,
            "Files": {},
            "FileSwaps": {
                "sound/voice/vo_emote/17462000.scd": "sound\\voice\\vo_emote\\17462000.scd",
"sound/voice/vo_emote/17462001.scd": "sound\\voice\\vo_emote\\17462001.scd",
"sound/voice/vo_emote/17462002.scd": "sound\\voice\\vo_emote\\17462002.scd",
"sound/voice/vo_emote/17462003.scd": "sound\\voice\\vo_emote\\17462003.scd",
"sound/voice/vo_emote/17462004.scd": "sound\\voice\\vo_emote\\17462004.scd",
"sound/voice/vo_emote/17462005.scd": "sound\\voice\\vo_emote\\17462005.scd",
"sound/voice/vo_emote/17462006.scd": "sound\\voice\\vo_emote\\17462006.scd",
"sound/voice/vo_emote/17462007.scd": "sound\\voice\\vo_emote\\17462007.scd",
"sound/voice/vo_emote/17462008.scd": "sound\\voice\\vo_emote\\17462008.scd",
"sound/voice/vo_emote/17462009.scd": "sound\\voice\\vo_emote\\17462009.scd",
"sound/voice/vo_emote/17462010.scd": "sound\\voice\\vo_emote\\17462010.scd",
"sound/voice/vo_emote/17462011.scd": "sound\\voice\\vo_emote\\17462011.scd",
"sound/voice/vo_emote/17462012.scd": "sound\\voice\\vo_emote\\17462012.scd",
"sound/voice/vo_emote/17462013.scd": "sound\\voice\\vo_emote\\17462013.scd",
"sound/voice/vo_emote/17462014.scd": "sound\\voice\\vo_emote\\17462014.scd",
"sound/voice/vo_emote/17462015.scd": "sound\\voice\\vo_emote\\17462015.scd"
            },
            "Manipulations": []
        },
{"Name": "Viera Feminine 2",
            "Description": "",
            "Priority": 40715,
            "Files": {},
            "FileSwaps": {
                "sound/voice/vo_emote/17462000.scd": "sound\\voice\\vo_emote\\17461000.scd",
"sound/voice/vo_emote/17462001.scd": "sound\\voice\\vo_emote\\17461001.scd",
"sound/voice/vo_emote/17462002.scd": "sound\\voice\\vo_emote\\17461002.scd",
"sound/voice/vo_emote/17462003.scd": "sound\\voice\\vo_emote\\17461003.scd",
"sound/voice/vo_emote/17462004.scd": "sound\\voice\\vo_emote\\17461004.scd",
"sound/voice/vo_emote/17462005.scd": "sound\\voice\\vo_emote\\17461005.scd",
"sound/voice/vo_emote/17462006.scd": "sound\\voice\\vo_emote\\17461006.scd",
"sound/voice/vo_emote/17462007.scd": "sound\\voice\\vo_emote\\17461007.scd",
"sound/voice/vo_emote/17462008.scd": "sound\\voice\\vo_emote\\17461008.scd",
"sound/voice/vo_emote/17462009.scd": "sound\\voice\\vo_emote\\17461009.scd",
"sound/voice/vo_emote/17462010.scd": "sound\\voice\\vo_emote\\17461010.scd",
"sound/voice/vo_emote/17462011.scd": "sound\\voice\\vo_emote\\17461011.scd",
"sound/voice/vo_emote/17462012.scd": "sound\\voice\\vo_emote\\17461012.scd",
"sound/voice/vo_emote/17462013.scd": "sound\\voice\\vo_emote\\17461013.scd",
"sound/voice/vo_emote/17462014.scd": "sound\\voice\\vo_emote\\17461014.scd",
"sound/voice/vo_emote/17462015.scd": "sound\\voice\\vo_emote\\17461015.scd"
            },
            "Manipulations": []
        },
{"Name": "Viera Feminine 3",
            "Description": "",
            "Priority": 40716,
            "Files": {},
            "FileSwaps": {
                "sound/voice/vo_emote/17462000.scd": "sound\\voice\\vo_emote\\17460000.scd",
"sound/voice/vo_emote/17462001.scd": "sound\\voice\\vo_emote\\17460001.scd",
"sound/voice/vo_emote/17462002.scd": "sound\\voice\\vo_emote\\17460002.scd",
"sound/voice/vo_emote/17462003.scd": "sound\\voice\\vo_emote\\17460003.scd",
"sound/voice/vo_emote/17462004.scd": "sound\\voice\\vo_emote\\17460004.scd",
"sound/voice/vo_emote/17462005.scd": "sound\\voice\\vo_emote\\17460005.scd",
"sound/voice/vo_emote/17462006.scd": "sound\\voice\\vo_emote\\17460006.scd",
"sound/voice/vo_emote/17462007.scd": "sound\\voice\\vo_emote\\17460007.scd",
"sound/voice/vo_emote/17462008.scd": "sound\\voice\\vo_emote\\17460008.scd",
"sound/voice/vo_emote/17462009.scd": "sound\\voice\\vo_emote\\17460009.scd",
"sound/voice/vo_emote/17462010.scd": "sound\\voice\\vo_emote\\17460010.scd",
"sound/voice/vo_emote/17462011.scd": "sound\\voice\\vo_emote\\17460011.scd",
"sound/voice/vo_emote/17462012.scd": "sound\\voice\\vo_emote\\17460012.scd",
"sound/voice/vo_emote/17462013.scd": "sound\\voice\\vo_emote\\17460013.scd",
"sound/voice/vo_emote/17462014.scd": "sound\\voice\\vo_emote\\17460014.scd",
"sound/voice/vo_emote/17462015.scd": "sound\\voice\\vo_emote\\17460015.scd"
            },
            "Manipulations": []
        },
{"Name": "Viera Feminine 4",
            "Description": "",
            "Priority": 40717,
            "Files": {},
            "FileSwaps": {
                "sound/voice/vo_emote/17462000.scd": "sound\\voice\\vo_emote\\17412000.scd",
"sound/voice/vo_emote/17462001.scd": "sound\\voice\\vo_emote\\17412001.scd",
"sound/voice/vo_emote/17462002.scd": "sound\\voice\\vo_emote\\17412002.scd",
"sound/voice/vo_emote/17462003.scd": "sound\\voice\\vo_emote\\17412003.scd",
"sound/voice/vo_emote/17462004.scd": "sound\\voice\\vo_emote\\17412004.scd",
"sound/voice/vo_emote/17462005.scd": "sound\\voice\\vo_emote\\17412005.scd",
"sound/voice/vo_emote/17462006.scd": "sound\\voice\\vo_emote\\17412006.scd",
"sound/voice/vo_emote/17462007.scd": "sound\\voice\\vo_emote\\17412007.scd",
"sound/voice/vo_emote/17462008.scd": "sound\\voice\\vo_emote\\17412008.scd",
"sound/voice/vo_emote/17462009.scd": "sound\\voice\\vo_emote\\17412009.scd",
"sound/voice/vo_emote/17462010.scd": "sound\\voice\\vo_emote\\17412010.scd",
"sound/voice/vo_emote/17462011.scd": "sound\\voice\\vo_emote\\17412011.scd",
"sound/voice/vo_emote/17462012.scd": "sound\\voice\\vo_emote\\17412012.scd",
"sound/voice/vo_emote/17462013.scd": "sound\\voice\\vo_emote\\17412013.scd",
"sound/voice/vo_emote/17462014.scd": "sound\\voice\\vo_emote\\17412014.scd",
"sound/voice/vo_emote/17462015.scd": "sound\\voice\\vo_emote\\17412015.scd"
            },
            "Manipulations": []
        },
{"Name": "Viera Feminine 5",
            "Description": "",
            "Priority": 40718,
            "Files": {},
            "FileSwaps": {
                "sound/voice/vo_emote/17462000.scd": "sound\\voice\\vo_emote\\17411000.scd",
"sound/voice/vo_emote/17462001.scd": "sound\\voice\\vo_emote\\17411001.scd",
"sound/voice/vo_emote/17462002.scd": "sound\\voice\\vo_emote\\17411002.scd",
"sound/voice/vo_emote/17462003.scd": "sound\\voice\\vo_emote\\17411003.scd",
"sound/voice/vo_emote/17462004.scd": "sound\\voice\\vo_emote\\17411004.scd",
"sound/voice/vo_emote/17462005.scd": "sound\\voice\\vo_emote\\17411005.scd",
"sound/voice/vo_emote/17462006.scd": "sound\\voice\\vo_emote\\17411006.scd",
"sound/voice/vo_emote/17462007.scd": "sound\\voice\\vo_emote\\17411007.scd",
"sound/voice/vo_emote/17462008.scd": "sound\\voice\\vo_emote\\17411008.scd",
"sound/voice/vo_emote/17462009.scd": "sound\\voice\\vo_emote\\17411009.scd",
"sound/voice/vo_emote/17462010.scd": "sound\\voice\\vo_emote\\17411010.scd",
"sound/voice/vo_emote/17462011.scd": "sound\\voice\\vo_emote\\17411011.scd",
"sound/voice/vo_emote/17462012.scd": "sound\\voice\\vo_emote\\17411012.scd",
"sound/voice/vo_emote/17462013.scd": "sound\\voice\\vo_emote\\17411013.scd",
"sound/voice/vo_emote/17462014.scd": "sound\\voice\\vo_emote\\17411014.scd",
"sound/voice/vo_emote/17462015.scd": "sound\\voice\\vo_emote\\17411015.scd"
            },
            "Manipulations": []
        },
{"Name": "Viera Feminine 6",
            "Description": "",
            "Priority": 40719,
            "Files": {},
            "FileSwaps": {
                "sound/voice/vo_emote/17462000.scd": "sound\\voice\\vo_emote\\17410000.scd",
"sound/voice/vo_emote/17462001.scd": "sound\\voice\\vo_emote\\17410001.scd",
"sound/voice/vo_emote/17462002.scd": "sound\\voice\\vo_emote\\17410002.scd",
"sound/voice/vo_emote/17462003.scd": "sound\\voice\\vo_emote\\17410003.scd",
"sound/voice/vo_emote/17462004.scd": "sound\\voice\\vo_emote\\17410004.scd",
"sound/voice/vo_emote/17462005.scd": "sound\\voice\\vo_emote\\17410005.scd",
"sound/voice/vo_emote/17462006.scd": "sound\\voice\\vo_emote\\17410006.scd",
"sound/voice/vo_emote/17462007.scd": "sound\\voice\\vo_emote\\17410007.scd",
"sound/voice/vo_emote/17462008.scd": "sound\\voice\\vo_emote\\17410008.scd",
"sound/voice/vo_emote/17462009.scd": "sound\\voice\\vo_emote\\17410009.scd",
"sound/voice/vo_emote/17462010.scd": "sound\\voice\\vo_emote\\17410010.scd",
"sound/voice/vo_emote/17462011.scd": "sound\\voice\\vo_emote\\17410011.scd",
"sound/voice/vo_emote/17462012.scd": "sound\\voice\\vo_emote\\17410012.scd",
"sound/voice/vo_emote/17462013.scd": "sound\\voice\\vo_emote\\17410013.scd",
"sound/voice/vo_emote/17462014.scd": "sound\\voice\\vo_emote\\17410014.scd",
"sound/voice/vo_emote/17462015.scd": "sound\\voice\\vo_emote\\17410015.scd"
            },
            "Manipulations": []
        },
{"Name": "Viera Feminine 7",
            "Description": "",
            "Priority": 40720,
            "Files": {},
            "FileSwaps": {
                "sound/voice/vo_emote/17462000.scd": "sound\\voice\\vo_emote\\17362000.scd",
"sound/voice/vo_emote/17462001.scd": "sound\\voice\\vo_emote\\17362001.scd",
"sound/voice/vo_emote/17462002.scd": "sound\\voice\\vo_emote\\17362002.scd",
"sound/voice/vo_emote/17462003.scd": "sound\\voice\\vo_emote\\17362003.scd",
"sound/voice/vo_emote/17462004.scd": "sound\\voice\\vo_emote\\17362004.scd",
"sound/voice/vo_emote/17462005.scd": "sound\\voice\\vo_emote\\17362005.scd",
"sound/voice/vo_emote/17462006.scd": "sound\\voice\\vo_emote\\17362006.scd",
"sound/voice/vo_emote/17462007.scd": "sound\\voice\\vo_emote\\17362007.scd",
"sound/voice/vo_emote/17462008.scd": "sound\\voice\\vo_emote\\17362008.scd",
"sound/voice/vo_emote/17462009.scd": "sound\\voice\\vo_emote\\17362009.scd",
"sound/voice/vo_emote/17462010.scd": "sound\\voice\\vo_emote\\17362010.scd",
"sound/voice/vo_emote/17462011.scd": "sound\\voice\\vo_emote\\17362011.scd",
"sound/voice/vo_emote/17462012.scd": "sound\\voice\\vo_emote\\17362012.scd",
"sound/voice/vo_emote/17462013.scd": "sound\\voice\\vo_emote\\17362013.scd",
"sound/voice/vo_emote/17462014.scd": "sound\\voice\\vo_emote\\17362014.scd",
"sound/voice/vo_emote/17462015.scd": "sound\\voice\\vo_emote\\17362015.scd"
            },
            "Manipulations": []
        },
{"Name": "Viera Feminine 8",
            "Description": "",
            "Priority": 40721,
            "Files": {},
            "FileSwaps": {
                "sound/voice/vo_emote/17462000.scd": "sound\\voice\\vo_emote\\17361000.scd",
"sound/voice/vo_emote/17462001.scd": "sound\\voice\\vo_emote\\17361001.scd",
"sound/voice/vo_emote/17462002.scd": "sound\\voice\\vo_emote\\17361002.scd",
"sound/voice/vo_emote/17462003.scd": "sound\\voice\\vo_emote\\17361003.scd",
"sound/voice/vo_emote/17462004.scd": "sound\\voice\\vo_emote\\17361004.scd",
"sound/voice/vo_emote/17462005.scd": "sound\\voice\\vo_emote\\17361005.scd",
"sound/voice/vo_emote/17462006.scd": "sound\\voice\\vo_emote\\17361006.scd",
"sound/voice/vo_emote/17462007.scd": "sound\\voice\\vo_emote\\17361007.scd",
"sound/voice/vo_emote/17462008.scd": "sound\\voice\\vo_emote\\17361008.scd",
"sound/voice/vo_emote/17462009.scd": "sound\\voice\\vo_emote\\17361009.scd",
"sound/voice/vo_emote/17462010.scd": "sound\\voice\\vo_emote\\17361010.scd",
"sound/voice/vo_emote/17462011.scd": "sound\\voice\\vo_emote\\17361011.scd",
"sound/voice/vo_emote/17462012.scd": "sound\\voice\\vo_emote\\17361012.scd",
"sound/voice/vo_emote/17462013.scd": "sound\\voice\\vo_emote\\17361013.scd",
"sound/voice/vo_emote/17462014.scd": "sound\\voice\\vo_emote\\17361014.scd",
"sound/voice/vo_emote/17462015.scd": "sound\\voice\\vo_emote\\17361015.scd"
            },
            "Manipulations": []
        },
{"Name": "Viera Feminine 9",
            "Description": "",
            "Priority": 40722,
            "Files": {},
            "FileSwaps": {
                "sound/voice/vo_emote/17462000.scd": "sound\\voice\\vo_emote\\17360000.scd",
"sound/voice/vo_emote/17462001.scd": "sound\\voice\\vo_emote\\17360001.scd",
"sound/voice/vo_emote/17462002.scd": "sound\\voice\\vo_emote\\17360002.scd",
"sound/voice/vo_emote/17462003.scd": "sound\\voice\\vo_emote\\17360003.scd",
"sound/voice/vo_emote/17462004.scd": "sound\\voice\\vo_emote\\17360004.scd",
"sound/voice/vo_emote/17462005.scd": "sound\\voice\\vo_emote\\17360005.scd",
"sound/voice/vo_emote/17462006.scd": "sound\\voice\\vo_emote\\17360006.scd",
"sound/voice/vo_emote/17462007.scd": "sound\\voice\\vo_emote\\17360007.scd",
"sound/voice/vo_emote/17462008.scd": "sound\\voice\\vo_emote\\17360008.scd",
"sound/voice/vo_emote/17462009.scd": "sound\\voice\\vo_emote\\17360009.scd",
"sound/voice/vo_emote/17462010.scd": "sound\\voice\\vo_emote\\17360010.scd",
"sound/voice/vo_emote/17462011.scd": "sound\\voice\\vo_emote\\17360011.scd",
"sound/voice/vo_emote/17462012.scd": "sound\\voice\\vo_emote\\17360012.scd",
"sound/voice/vo_emote/17462013.scd": "sound\\voice\\vo_emote\\17360013.scd",
"sound/voice/vo_emote/17462014.scd": "sound\\voice\\vo_emote\\17360014.scd",
"sound/voice/vo_emote/17462015.scd": "sound\\voice\\vo_emote\\17360015.scd"
            },
            "Manipulations": []
        },
{"Name": "Viera Feminine 10",
            "Description": "",
            "Priority": 40723,
            "Files": {},
            "FileSwaps": {
                "sound/voice/vo_emote/17462000.scd": "sound\\voice\\vo_emote\\17312000.scd",
"sound/voice/vo_emote/17462001.scd": "sound\\voice\\vo_emote\\17312001.scd",
"sound/voice/vo_emote/17462002.scd": "sound\\voice\\vo_emote\\17312002.scd",
"sound/voice/vo_emote/17462003.scd": "sound\\voice\\vo_emote\\17312003.scd",
"sound/voice/vo_emote/17462004.scd": "sound\\voice\\vo_emote\\17312004.scd",
"sound/voice/vo_emote/17462005.scd": "sound\\voice\\vo_emote\\17312005.scd",
"sound/voice/vo_emote/17462006.scd": "sound\\voice\\vo_emote\\17312006.scd",
"sound/voice/vo_emote/17462007.scd": "sound\\voice\\vo_emote\\17312007.scd",
"sound/voice/vo_emote/17462008.scd": "sound\\voice\\vo_emote\\17312008.scd",
"sound/voice/vo_emote/17462009.scd": "sound\\voice\\vo_emote\\17312009.scd",
"sound/voice/vo_emote/17462010.scd": "sound\\voice\\vo_emote\\17312010.scd",
"sound/voice/vo_emote/17462011.scd": "sound\\voice\\vo_emote\\17312011.scd",
"sound/voice/vo_emote/17462012.scd": "sound\\voice\\vo_emote\\17312012.scd",
"sound/voice/vo_emote/17462013.scd": "sound\\voice\\vo_emote\\17312013.scd",
"sound/voice/vo_emote/17462014.scd": "sound\\voice\\vo_emote\\17312014.scd",
"sound/voice/vo_emote/17462015.scd": "sound\\voice\\vo_emote\\17312015.scd"
            },
            "Manipulations": []
        },
{"Name": "Viera Feminine 11",
            "Description": "",
            "Priority": 40724,
            "Files": {},
            "FileSwaps": {
                "sound/voice/vo_emote/17462000.scd": "sound\\voice\\vo_emote\\17311000.scd",
"sound/voice/vo_emote/17462001.scd": "sound\\voice\\vo_emote\\17311001.scd",
"sound/voice/vo_emote/17462002.scd": "sound\\voice\\vo_emote\\17311002.scd",
"sound/voice/vo_emote/17462003.scd": "sound\\voice\\vo_emote\\17311003.scd",
"sound/voice/vo_emote/17462004.scd": "sound\\voice\\vo_emote\\17311004.scd",
"sound/voice/vo_emote/17462005.scd": "sound\\voice\\vo_emote\\17311005.scd",
"sound/voice/vo_emote/17462006.scd": "sound\\voice\\vo_emote\\17311006.scd",
"sound/voice/vo_emote/17462007.scd": "sound\\voice\\vo_emote\\17311007.scd",
"sound/voice/vo_emote/17462008.scd": "sound\\voice\\vo_emote\\17311008.scd",
"sound/voice/vo_emote/17462009.scd": "sound\\voice\\vo_emote\\17311009.scd",
"sound/voice/vo_emote/17462010.scd": "sound\\voice\\vo_emote\\17311010.scd",
"sound/voice/vo_emote/17462011.scd": "sound\\voice\\vo_emote\\17311011.scd",
"sound/voice/vo_emote/17462012.scd": "sound\\voice\\vo_emote\\17311012.scd",
"sound/voice/vo_emote/17462013.scd": "sound\\voice\\vo_emote\\17311013.scd",
"sound/voice/vo_emote/17462014.scd": "sound\\voice\\vo_emote\\17311014.scd",
"sound/voice/vo_emote/17462015.scd": "sound\\voice\\vo_emote\\17311015.scd"
            },
            "Manipulations": []
        },
{"Name": "Viera Feminine 12",
            "Description": "",
            "Priority": 40725,
            "Files": {},
            "FileSwaps": {
                "sound/voice/vo_emote/17462000.scd": "sound\\voice\\vo_emote\\17310000.scd",
"sound/voice/vo_emote/17462001.scd": "sound\\voice\\vo_emote\\17310001.scd",
"sound/voice/vo_emote/17462002.scd": "sound\\voice\\vo_emote\\17310002.scd",
"sound/voice/vo_emote/17462003.scd": "sound\\voice\\vo_emote\\17310003.scd",
"sound/voice/vo_emote/17462004.scd": "sound\\voice\\vo_emote\\17310004.scd",
"sound/voice/vo_emote/17462005.scd": "sound\\voice\\vo_emote\\17310005.scd",
"sound/voice/vo_emote/17462006.scd": "sound\\voice\\vo_emote\\17310006.scd",
"sound/voice/vo_emote/17462007.scd": "sound\\voice\\vo_emote\\17310007.scd",
"sound/voice/vo_emote/17462008.scd": "sound\\voice\\vo_emote\\17310008.scd",
"sound/voice/vo_emote/17462009.scd": "sound\\voice\\vo_emote\\17310009.scd",
"sound/voice/vo_emote/17462010.scd": "sound\\voice\\vo_emote\\17310010.scd",
"sound/voice/vo_emote/17462011.scd": "sound\\voice\\vo_emote\\17310011.scd",
"sound/voice/vo_emote/17462012.scd": "sound\\voice\\vo_emote\\17310012.scd",
"sound/voice/vo_emote/17462013.scd": "sound\\voice\\vo_emote\\17310013.scd",
"sound/voice/vo_emote/17462014.scd": "sound\\voice\\vo_emote\\17310014.scd",
"sound/voice/vo_emote/17462015.scd": "sound\\voice\\vo_emote\\17310015.scd"
            },
            "Manipulations": []
        }]
    }